loqedAPI/__init__.py
loqedAPI/apiclient.py
loqedAPI/const.py
loqedAPI/exceptions.py
loqedAPI/loqed.py
loqedAPI-0.1.0.dist-info/LICENSE
loqedAPI-0.1.0.dist-info/METADATA
loqedAPI-0.1.0.dist-info/WHEEL
loqedAPI-0.1.0.dist-info/top_level.txt
loqedAPI-0.1.0.dist-info/RECORD
