Metadata-Version: 2.1
Name: loqedAPI
Version: 0.1.0
Summary: Python package to use the Loqed Smart Door Lock APIs. To be used by Home Assistant.
Home-page: https://github.com/cpolhout/loqedAPI
Author: Casper Polhout
Author-email: cpolhout@gmail.com
License: BSD 2-clause
Project-URL: Bug Tracker, https://github.com/cpolhout/loqedAPI/issues
Platform: UNKNOWN
Classifier: Development Status :: 1 - Planning
Classifier: Intended Audience :: Science/Research
Classifier: License :: OSI Approved :: BSD License
Classifier: Operating System :: POSIX :: Linux
Classifier: Programming Language :: Python :: 2
Classifier: Programming Language :: Python :: 2.7
Classifier: Programming Language :: Python :: 3
Classifier: Programming Language :: Python :: 3.4
Classifier: Programming Language :: Python :: 3.5
Requires-Python: >=3.6
License-File: LICENSE
Requires-Dist: aiohttp
Requires-Dist: async-timeout
